dataclass_mage/__init__.py
dataclass_mage/__version__.py
dataclass_mage/abstractions.py
dataclass_mage/bases.py
dataclass_mage/bases_meta.py
dataclass_mage/class_helper.py
dataclass_mage/constants.py
dataclass_mage/decorators.py
dataclass_mage/dumpers.py
dataclass_mage/enums.py
dataclass_mage/errors.py
dataclass_mage/lazy_imports.py
dataclass_mage/loaders.py
dataclass_mage/log.py
dataclass_mage/models.py
dataclass_mage/parsers.py
dataclass_mage/property_wizard.py
dataclass_mage/serial_json.py
dataclass_mage/type_def.py
dataclass_mage/wizard_mixins.py
dataclass_mage/utils/__init__.py
dataclass_mage/utils/dict_helper.py
dataclass_mage/utils/lazy_loader.py
dataclass_mage/utils/string_conv.py
dataclass_mage/utils/type_conv.py
dataclass_mage/utils/typing_compat.py
dataclass_mage/utils/wrappers.py
dataclass_mage/wizard_cli/__init__.py
dataclass_mage/wizard_cli/cli.py
dataclass_mage/wizard_cli/schema.py
dataclass_mage-0.25.1.dist-info/LICENSE
dataclass_mage-0.25.1.dist-info/METADATA
dataclass_mage-0.25.1.dist-info/WHEEL
dataclass_mage-0.25.1.dist-info/entry_points.txt
dataclass_mage-0.25.1.dist-info/top_level.txt
dataclass_mage-0.25.1.dist-info/RECORD
