Metadata-Version: 2.1
Name: dataclass-mage
Version: 0.25.1
Summary: Marshal dataclasses to/from JSON. Use field properties with initial values. Construct a dataclass schema with JSON input.
Author: Steven Hogue
License: Apache 2.0
Project-URL: Documentation, https://.readthedocs.io
Project-URL: Source, https://github.com/Frequency0/dataclass-mage
Keywords: dataclasses,dataclass,wizard,json,marshal,json to dataclass,json2dataclass,dict to dataclass,property,field-property,serialization,deserialization
Classifier: Development Status :: 5 - Production/Stable
Classifier: Intended Audience :: Developers
Classifier: License :: OSI Approved :: Apache Software License
Classifier: Natural Language :: English
Classifier: Programming Language :: Python :: 3 :: Only
Classifier: Programming Language :: Python :: 3.9
Classifier: Programming Language :: Python :: 3.10
Classifier: Programming Language :: Python :: 3.11
Classifier: Programming Language :: Python
License-File: LICENSE
Provides-Extra: timedelta
Requires-Dist: pytimeparse >=1.1.7 ; extra == 'timedelta'
Provides-Extra: yaml
Requires-Dist: PyYAML >=5.3 ; extra == 'yaml'
